{
  "resourceType": "Device",
  "id": "uc4ACMEPacemaker",
  "meta": {
    "profile": [
      "http://hl7.org/fhir/uv/cardx-cied/StructureDefinition/cied-device"
    ]
  },
  "type": [
    {
      "coding": [
        {
          "code": "753665",
          "system": "urn:iso:std:iso:11073:10101"
        }
      ]
    }
  ],
  "gateway": [
    {
      "reference": {
        "reference": "Device/uc4CIEDMonitor"
      }
    }
  ],
  "manufacturer": "ACME Devices",
  "serialNumber": "uc4ACMEPacemaker",
  "modelNumber": "PacemakerExample4"
}
