{
  "resourceType": "ValueSet",
  "status": "active",
  "name": "CIEDMonitorTypesVS",
  "id": "cied-monitor-types-vs",
  "title": "CIED Monitor Types",
  "description": "The type of CIED monitor",
  "url": "http://hl7.org/fhir/uv/cardx-cied/ValueSet/cied-monitor-types-vs",
  "experimental": false,
  "compose": {
    "include": [
      {
        "system": "http://hl7.org/fhir/uv/cardx-cied/CodeSystem/CardXCIED",
        "concept": [
          {
            "code": "bedside-device",
            "display": "Bedside Monitor"
          },
          {
            "code": "mobile-monitor",
            "display": "Mobile App"
          },
          {
            "code": "portable-device",
            "display": "Portable Device"
          }
        ]
      }
    ]
  }
}
